VIStk/Form.zip
VIStk/VIS.py
VIStk/__init__.py
VIStk/fUtil.py
VIStk/Objects/_Layout.py
VIStk/Objects/_Root.py
VIStk/Objects/_SubRoot.py
VIStk/Objects/_Window.py
VIStk/Objects/_WindowGeometry.py
VIStk/Objects/__init__.py
VIStk/Structures/Installer.py
VIStk/Structures/_Project.py
VIStk/Structures/_Release.py
VIStk/Structures/_Screen.py
VIStk/Structures/_VINFO.py
VIStk/Structures/_Version.py
VIStk/Structures/__init__.py
VIStk/Templates/collect.txt
VIStk/Templates/f_element.txt
VIStk/Templates/m_elements.txt
VIStk/Templates/screen.txt
VIStk/Templates/spec.txt
VIStk/Templates/version.txt
VIStk/Templates/Widgets/THE_PLAN
VIStk/Templates/Widgets/button.txt
VIStk/Templates/Widgets/combobox.txt
VIStk/Templates/Widgets/entry.txt
VIStk/Templates/Widgets/label.txt
VIStk/Widgets/_LayoutFrame.py
VIStk/Widgets/_MenuItem.py
VIStk/Widgets/_MenuWindow.py
VIStk/Widgets/_QuestionWindow.py
VIStk/Widgets/_VISMenu.py
VIStk/Widgets/_WarningWindow.py
VIStk/Widgets/__init__.py
vistk-0.3.15.2.dist-info/licenses/LICENSE
vistk-0.3.15.2.dist-info/METADATA
vistk-0.3.15.2.dist-info/WHEEL
vistk-0.3.15.2.dist-info/entry_points.txt
vistk-0.3.15.2.dist-info/top_level.txt
vistk-0.3.15.2.dist-info/RECORD
