Metadata-Version: 2.4
Name: VIStk
Version: 0.3.15.2
Summary: Visual Interfacing Structure for python using tkinter
Author-email: Elijah Love <elijah2005l@gmail.com>
Maintainer-email: Elijah Love <elijah2005l@gmail.com>
License: BSD 2-Clause License
Project-URL: Homepage, https://github.com/KarlTheKrazyKat/VIS/blob/master/README.md
Project-URL: Documentation, https://github.com/KarlTheKrazyKat/VIS/blob/master/documentation.md
Project-URL: Repository, https://github.com/KarlTheKrazyKat/VIS/
Project-URL: Bug Tracker, https://github.com/KarlTheKrazyKat/VIS/blob/master/knownissues.md
Project-URL: Changelog, https://github.com/KarlTheKrazyKat/VIS/blob/master/changelog.md
Keywords: python,gui
Classifier: Development Status :: 2 - Pre-Alpha
Classifier: Programming Language :: Python
Requires-Python: >=3.10
License-File: LICENSE
Requires-Dist: pyinstaller
Dynamic: license-file
